lhs_mcp_demov1_0/__init__.py
lhs_mcp_demov1_0-0.1.0.dist-info/WHEEL
lhs_mcp_demov1_0-0.1.0.dist-info/entry_points.txt
lhs_mcp_demov1_0-0.1.0.dist-info/METADATA
lhs_mcp_demov1_0-0.1.0.dist-info/RECORD
